{
  "NONE": {
    "name": "",
    "buildings": [],
    "speeds": []
  },
  "SMELT": {
    "name": "Smelting facility",
    "buildings": [2302],
    "speeds": [1]
  },
  "CHEMICAL": {
    "name": "Chemical facility",
    "buildings": [2309],
    "speeds": [1]
  },
  "REFINE": {
    "name": "Refining facility",
    "buildings": [2308],
    "speeds": [1]
  },
  "ASSEMBLE": {
    "name": "Assembler",
    "buildings": [2303, 2304, 2305],
    "speeds": [0.75, 1, 1.5]
  },
  "PARTICLE": {
    "name": "Particle collider",
    "buildings": [2310],
    "speeds": [1]
  },
  "EXCHANGE": {
    "name": "Energy exchanger",
    "buildings": [2209]
  },
  "PHOTON_STORE": {
    "name": "Ray reciever",
    "buildings": [2208],
    "speeds": [1]
  },
  "FRACTIONATE": {
    "name": "Fractionation facility",
    "buildings": [2314],
    "speeds": [1]
  },
  "RESEARCH": {
    "name": "Research facility",
    "buildings": [2901],
    "speeds": [1]
  },

  "GATHER": {
    "name": "Mecha",
    "buildings": [1001],
    "speeds": [1]
  },
  "MINE": {
    "name": "Miner",
    "buildings": [2301],
    "speeds": [1]
  },
  "PUMP": {
    "name": "Pump",
    "buildings": [2306],
    "speeds": [1]
  },
  "ORBITAL_COLLECT": {
    "name": "Orbital Collector",
    "buildings": [2105],
    "speeds": [1]
  },
  "OIL_EXTRACT": {
    "name": "Oil extractor",
    "buildings":  [2307],
    "speeds": [1]
  }
}